qarray/__init__.py
qarray/functions.py
qarray/DotArrays/ChargeSensedDotArray.py
qarray/DotArrays/DotArray.py
qarray/DotArrays/GateVoltageComposer.py
qarray/DotArrays/__init__.py
qarray/DotArrays/_helper_functions.py
qarray/DotArrays/ground_state.py
qarray/gui/__init__.py
qarray/gui/gui.py
qarray/gui/gui_charge_sensor.py
qarray/gui/helper_functions.py
qarray/jax_implementations/__init__.py
qarray/jax_implementations/helper_functions.py
qarray/jax_implementations/brute_force_jax/__init__.py
qarray/jax_implementations/brute_force_jax/closed.py
qarray/jax_implementations/brute_force_jax/open.py
qarray/jax_implementations/brute_force_jax/charge_configuration_generators/__init__.py
qarray/jax_implementations/brute_force_jax/charge_configuration_generators/open_dot_configurations.py
qarray/jax_implementations/default_jax/__init__.py
qarray/jax_implementations/default_jax/closed.py
qarray/jax_implementations/default_jax/open.py
qarray/jax_implementations/default_jax/charge_configuration_generators/__init__.py
qarray/jax_implementations/default_jax/charge_configuration_generators/open_dot_configurations.py
qarray/latching_models/LatchingBaseModel.py
qarray/latching_models/LeadLatching.py
qarray/latching_models/PSBLatching.py
qarray/latching_models/__init__.py
qarray/noise_models/BaseNoiseModel.py
qarray/noise_models/NoNoise.py
qarray/noise_models/TelegraphNoise.py
qarray/noise_models/WhiteNoise.py
qarray/noise_models/__init__.py
qarray/python_implementations/__init__.py
qarray/python_implementations/helper_functions.py
qarray/python_implementations/brute_force_python/__init__.py
qarray/python_implementations/brute_force_python/closed.py
qarray/python_implementations/brute_force_python/open.py
qarray/python_implementations/brute_force_python/charge_configuration_generators/__init__.py
qarray/python_implementations/brute_force_python/charge_configuration_generators/open_dot_configurations.py
qarray/python_implementations/default_and_thresholded_python/__init__.py
qarray-1.6.0.dist-info/licenses/LICENSE
qarray-1.6.0.dist-info/WHEEL
qarray-1.6.0.dist-info/METADATA
qarray-1.6.0.dist-info/RECORD
