Metadata-Version: 2.4
Name: qarray
Version: 1.6.0
Summary: Qarray, a GPU accelerated quantum dot array simulator, leveraging parallelised Rust and JAX XLA acceleration
Keywords: semiconducting,quantum dots,quantum,simulation,GPU,rust,jax,quantum computing,quantum programming,quantum simulation,quantum optimization
Author-email: Barnaby van Straaten <b.l.vanstraaten@tudelft.nl>, Joseph Hickie <joseph.hickie@trinity.ox.ac.uk>, Jonas Schuff <jonas.schuffn@materials.ox.ac.uk>, Cornelius Carlsson <cornelius.carlsson@eng.ox.ac.uk>
Requires-Python: >=3.10
Classifier: Operating System :: OS Independent
Classifier: Intended Audience :: Science/Research
Classifier: Intended Audience :: Developers
Classifier: Topic :: Scientific/Engineering
Classifier: License :: OSI Approved :: Mozilla Public License 2.0 (MPL 2.0)
Classifier: Programming Language :: Python :: 3.10
Classifier: Programming Language :: Python :: 3.11
License-File: LICENSE
Requires-Dist: qarray-rust-core==1.3.1
Requires-Dist: osqp==1.0.0
Requires-Dist: numpy==2.2.4
Requires-Dist: pandas>=2.2
Requires-Dist: dash>=2.17
Requires-Dist: scipy>=1.11
Requires-Dist: matplotlib>=3.8
Requires-Dist: loguru>=0.5
Requires-Dist: jax[cpu]>=0.2
Requires-Dist: jaxopt>=0.4
Requires-Dist: tqdm>=4.62
Requires-Dist: plotly>=5.22
Requires-Dist: dash>=2.17
Project-URL: Documentation, https://qarray.readthedocs.io/en/latest/
Project-URL: Home, https://github.com/b-vanstraaten/qarray
Project-URL: Issues, https://github.com/b-vanstraaten/qarray/issues
Project-URL: Repository, https://github.com/b-vanstraaten/qarray
